README.rst
setup.py
qiita_v2/__init__.py
qiita_v2/client.py
qiita_v2/client_base.py
qiita_v2/exception.py
qiita_v2/response.py
qiita_v2.egg-info/PKG-INFO
qiita_v2.egg-info/SOURCES.txt
qiita_v2.egg-info/dependency_links.txt
qiita_v2.egg-info/requires.txt
qiita_v2.egg-info/top_level.txt