Metadata-Version: 1.1
Name: qiita-v2
Version: 0.1.1
Summary: Python Wrapper for Qiita API v2
Home-page: http://github.com/petitviolet/qiita_py
Author: petitviolet
Author-email: violethero0820@gmail.com
License: MIT
Platform: any
Classifier: Environment :: Web Environment
Classifier: Intended Audience :: Developers
Classifier: Operating System :: OS Independent
Classifier: Programming Language :: Python
Classifier: Topic :: Software Development
